chameleon_partials/__init__.py
chameleon_partials-0.1.0.dist-info/LICENSE
chameleon_partials-0.1.0.dist-info/METADATA
chameleon_partials-0.1.0.dist-info/WHEEL
chameleon_partials-0.1.0.dist-info/top_level.txt
chameleon_partials-0.1.0.dist-info/RECORD
