Metadata-Version: 2.1
Name: chameleon-partials
Version: 0.1.0
Summary: Simple reuse of partial HTML page templates in the Chameleon template language for Python web frameworks.
Home-page: https://github.com/mikeckennedy/chameleon_partials
Author: Michael Kennedy
Author-email: michael@talkpython.fm
License: MIT
Platform: UNKNOWN
Classifier: Development Status :: 2 - Pre-Alpha
Classifier: License :: OSI Approved :: MIT License
Classifier: Programming Language :: Python
Classifier: Programming Language :: Python :: 3
Classifier: Programming Language :: Python :: 3.6
Classifier: Programming Language :: Python :: 3.7
Classifier: Programming Language :: Python :: 3.8
Classifier: Programming Language :: Python :: 3.9
Classifier: Programming Language :: Python :: 3.10
License-File: LICENSE
Requires-Dist: chameleon
